cleanup_sims/__init__.py
cleanup_sims/cleanup_sims.py
cleanup_sims-0.0.1.dist-info/LICENSE
cleanup_sims-0.0.1.dist-info/METADATA
cleanup_sims-0.0.1.dist-info/WHEEL
cleanup_sims-0.0.1.dist-info/entry_points.txt
cleanup_sims-0.0.1.dist-info/top_level.txt
cleanup_sims-0.0.1.dist-info/RECORD
