Metadata-Version: 2.1
Name: cleanup-sims
Version: 0.0.1
Summary: Cleans up your messy Gromacs simulations
Author-email: Kevin Sawade <kevin.sawade@uni-konstanz.de>
License: GNU LESSER GENERAL PUBLIC LICENSE
Keywords: gromacs,molecular-dynamics
Requires-Python: >=3.9
License-File: LICENSE
Requires-Dist: MDAnalysis
Requires-Dist: numpy
Requires-Dist: imohash
